src/modulos/5_3sevenseg/src/design/top.sv
// MODULO 5.2 - Seven Segment Display
// Autor: Andres Obregon Lopez
// Circuito combinacional para el display de 7 segmentos en representacion hexadecimal (0-F)

module top (
    input logic [3:0] sw,           // Bits de entrada: AIN ,BIN ,CIN ,DIN (MSB a LSB)
    output logic [6:0] segments     // Segments: SA, SB, SC, SD, SE, SF, SG (LSB a MSB)
);

/*Asignacion de los bits de entrada */
assign AIN = sw[3];
assign BIN = sw[2];
assign CIN = sw[1];
assign DIN = sw[0];

/*Asignacion de los bits de salida */
assign SA = segments[0];
assign SB = segments[1];
assign SC = segments[2];
assign SD = segments[3];
assign SE = segments[4];
assign SF = segments[5];
assign SG = segments[6];

/*Asignacion de operadores logicos reutilizados - NOT*/
assign AIN_N = ~AIN;
assign BIN_N = ~BIN;
assign CIN_N = ~CIN;
assign DIN_N = ~DIN;

/*Expresiones logicas para cada segmento*/

//Segmento A: SA = Din'(Ain+Bin')+Ain'(Cin+BinDin)+BinCin+AinBin'Cin'
assign SA = (DIN_N) & (AIN | BIN_N) | 
            (AIN_N) & (CIN | (BIN & DIN)) | 
            (BIN & CIN) | 
            (AIN & BIN_N & CIN_N);  

//Segmento B: SB = Bin'(Ain' + Din') + Ain'(Cin ⊙ Din) + Ain Din Cin'
assign SB = (BIN_N) & (AIN_N | DIN_N) | 
            (AIN_N) & (~(CIN ^ DIN)) | 
            (AIN & DIN & CIN_N);

//Segmento C: SC = AinBin' + Ain'(Bin + Din + Cin') + DinCin'
assign SC = (AIN & BIN_N) | 
            (AIN_N) & (BIN | DIN | CIN_N) | 
            (DIN & CIN_N);   

//Segmento D: SD = Din'(Ain'Bin' + BinCin + AinCin') + Din(BinCin' + Bin'Cin)
assign SD = (DIN_N & (AIN_N & BIN_N | BIN & CIN | AIN & CIN_N)) | 
            (DIN & (BIN & CIN_N | BIN_N & CIN));

//Segmento E: SE = Din'(Bin'+Cin) + Ain(Cin + Bin)
assign SE = (DIN_N & (BIN_N | CIN)) | 
            (AIN & (CIN | BIN));

//Segmento F: SF = Ain(Cin + Bin') + Din'(Bin + Cin') + Ain'BinCin'
assign SF = (AIN & (CIN | BIN_N)) | 
            (DIN_N & (BIN | CIN_N)) | 
            (AIN_N & BIN & CIN_N);

//Segmento G: SG = Ain(Din + Bin') + Cin(Bin' + Din') + Ain'BinCin'
assign SG = (AIN & (DIN | BIN_N)) | 
            (CIN & (BIN_N | DIN_N)) | 
            (AIN_N & BIN & CIN_N);

endmodule

src/modulos/5_3sevenseg/src/sim/top_tb.sv
`timescale 1ns/1ps

module top_tb;
    /*
    Observe que en esta seccion los logic no se definen como input o output, son propios del modulo
    como si fueran un nodo, por eso se conectan en el DUT. 
    */
    logic [3:0] sw;                         
    logic Sa, Sb, Sc, Sd, Se, Sf, Sg;
    logic [6:0] out;

    // DUT (Device Under Test)

    /*
    Observe que .sw se refiere al nodo sw creado en este propio modulo, (sw) se refiere al input 
    definido en el top. Se recomienda usar los mismos nombres porque esto permite seguir trabajando
    con el mismo nombre de variable y la conexion es mas facil. De igual forma para las demas.

    Observe que se prefiere usar los S# porque es mas facil y corto que escribir segments[#]...
    */
    top dut (
        .sw(sw),
        .segments({Sg,Sf,Se,Sd,Sc,Sb,Sa})
    );

    // Función que devuelve patrón esperado. Se utilizara para comparar 'segments' contra 'expected'
    function automatic [6:0] expected (input [3:0] val);
        case (val)
            4'd0: expected = 7'b1111110;
            4'd1: expected = 7'b0110000;
            4'd2: expected = 7'b1101101;
            4'd3: expected = 7'b1111001;
            4'd4: expected = 7'b0110011;
            4'd5: expected = 7'b1011011;
            4'd6: expected = 7'b1011111;
            4'd7: expected = 7'b1110000;
            4'd8: expected = 7'b1111111;
            4'd9: expected = 7'b1110011;
            4'd10: expected = 7'b1110111; // A
            4'd11: expected = 7'b0011111; // B
            4'd12: expected = 7'b1001110; // C
            4'd13: expected = 7'b0111101; // D
            4'd14: expected = 7'b1001111; // E
            4'd15: expected = 7'b1000111; // F

            default: expected = 7'b0000000;
        endcase
    endfunction

    initial begin
        $display("Starting exhaustive test...");

        for (int i = 0; i < 16; i++) begin
            sw = i;
            #1;
            out = {Sg,Sf,Se,Sd,Sc,Sb,Sa};       

            if (out != expected(i)) begin
                $display("ERROR at %0d -> got %b expected %b",
                         i, out, expected(i));
            end
            else begin
                $display("OK %0d -> %b", i, out);
            end
        end

        $display("Test finished");
        $finish;
    end

    initial begin
        $dumpfile("top_tb.vcd");
        $dumpvars(0,top_tb);
    end

endmodule

src/modulos/5_3sevenseg/src/build/top_tb.vcd
$date
	Sun Mar 29 22:30:48 2026
$end
$version
	Icarus Verilog
$end
$timescale
	1ps
$end
$scope module top_tb $end
$var wire 1 ! Sg $end
$var wire 1 " Sf $end
$var wire 1 # Se $end
$var wire 1 $ Sd $end
$var wire 1 % Sc $end
$var wire 1 & Sb $end
$var wire 1 ' Sa $end
$var reg 7 ( out [6:0] $end
$var reg 4 ) sw [3:0] $end
$scope function expected $end
$upscope $end
$scope module dut $end
$var wire 1 * AIN_N $end
$var wire 1 + BIN_N $end
$var wire 1 , CIN_N $end
$var wire 1 - DIN_N $end
$var wire 1 . SA $end
$var wire 1 / SB $end
$var wire 1 0 SC $end
$var wire 1 1 SD $end
$var wire 1 2 SE $end
$var wire 1 3 SF $end
$var wire 1 4 SG $end
$var wire 4 5 sw [3:0] $end
$var wire 1 6 DIN $end
$var wire 1 7 CIN $end
$var wire 1 8 BIN $end
$var wire 1 9 AIN $end
$var reg 7 : segments [6:0] $end
$upscope $end
$scope begin $ivl_for_loop0 $end
$var integer 32 ; i [31:0] $end
$upscope $end
$upscope $end
$enddefinitions $end
$comment Show the parameter values. $end
$dumpall
$end
#0
$dumpvars
b0 ;
bx :
09
08
07
06
b0 5
x4
x3
x2
x1
x0
x/
x.
1-
1,
1+
1*
b0 )
bx (
x'
x&
x%
x$
x#
x"
x!
$end
#1000
0-
16
b1 )
b1 5
b1 ;
#2000
0,
1-
17
06
b10 )
b10 5
b10 ;
#3000
0-
16
b11 )
b11 5
b11 ;
#4000
0+
1,
1-
18
07
06
b100 )
b100 5
b100 ;
#5000
0-
16
b101 )
b101 5
b101 ;
#6000
0,
1-
17
06
b110 )
b110 5
b110 ;
#7000
0-
16
b111 )
b111 5
b111 ;
#8000
0*
1+
1,
1-
19
08
07
06
b1000 )
b1000 5
b1000 ;
#9000
0-
16
b1001 )
b1001 5
b1001 ;
#10000
0,
1-
17
06
b1010 )
b1010 5
b1010 ;
#11000
0-
16
b1011 )
b1011 5
b1011 ;
#12000
0+
1,
1-
18
07
06
b1100 )
b1100 5
b1100 ;
#13000
0-
16
b1101 )
b1101 5
b1101 ;
#14000
0,
1-
17
06
b1110 )
b1110 5
b1110 ;
#15000
0-
16
b1111 )
b1111 5
b1111 ;
#16000
b10000 ;
