src/Emisor/design/top.sv
// ============================================================
// MODULO PRINCIPAL: Emisor con codificador Hamming(7,4)
// Integra:
// 1) hamming74_encoder
// 2) bin_to_7seg
// 3) error_inserter
//
// Autor base: Andres Obregon Lopez / Mariana Solano Gutierrez
// Integracion realizada en un solo archivo
// ============================================================



// ============================================================
// TOP MODULE
// ============================================================
module top (
    input  logic [3:0] data_in,        // Dato original de 4 bits
    input  logic [2:0] BitError,       // 0 = sin error, 1..7 = bit a alterar
    output logic [6:0] code_out,       // Palabra Hamming generada
    output logic [6:0] transmision,    // Palabra transmitida con posible error
    output logic [6:0] seg             // Display 7 segmentos del dato original
);
    // --------------------------------------------------------
    // Instancia del decodificador a 7 segmentos
    // Aquí se muestra el dato original de 4 bits
    // --------------------------------------------------------

    bin_to_7seg U3 (
    .sw(data_in),
    .segments(seg)
    );

    /*
    bin_to_7seg #(
        .COMMON_ANODE(1'b0)
    ) U3 (
        .bin_in (data_in),
        .seg    (seg)
    );
*/








    // --------------------------------------------------------
    // Instancia del codificador Hamming(7,4)
    // --------------------------------------------------------
    hamming74_encoder U1 (
        .data_in  (data_in),
        .code_out (code_out)
    );

    // --------------------------------------------------------
    // Instancia del generador/inserción de error
    // --------------------------------------------------------
    error_inserter U2 (
        .BitError    (BitError),
        .WordHamming (code_out),
        .transmision (transmision)
    );

endmodule



// ============================================================
// MODULO 5.1: Paridad Par Hamming(7,4)
// ============================================================
module hamming74_encoder (
    input  logic [3:0] data_in,   // {d3,d2,d1,d0}
    output logic [6:0] code_out   // {p1,p2,d3,p4,d2,d1,d0}
);

    logic p1, p2, p4;

    always_comb begin
        // Paridad par
        p1 = data_in[3] ^ data_in[2] ^ data_in[0];
        p2 = data_in[3] ^ data_in[1] ^ data_in[0];
        p4 = data_in[2] ^ data_in[1] ^ data_in[0];

        // Palabra Hamming (7,4)
        code_out[6] = p1;         // posición 1
        code_out[5] = p2;         // posición 2
        code_out[4] = data_in[3]; // posición 3 = d3
        code_out[3] = p4;         // posición 4
        code_out[2] = data_in[2]; // posición 5 = d2
        code_out[1] = data_in[1]; // posición 6 = d1
        code_out[0] = data_in[0]; // posición 7 = d0
    end

endmodule



// ============================================================
// MODULO 5.2: Display de 7 segmentos
// ============================================================
module bin_to_7seg (
    input logic [3:0] sw,           // Bits de entrada: AIN ,BIN ,CIN ,DIN (MSB a LSB)
    output logic [6:0] segments     // Segments: SA, SB, SC, SD, SE, SF, SG (LSB a MSB)
);
// Definicion de bits de entrada y sus negados para facilitar la expresion de las funciones logicas de cada segmento
logic AIN, BIN, CIN, DIN;
logic AIN_N, BIN_N, CIN_N, DIN_N;
logic SA, SB, SC, SD, SE, SF, SG;

/*Asignacion de los bits de entrada */
assign AIN = sw[3];
assign BIN = sw[2];
assign CIN = sw[1];
assign DIN = sw[0];

/*Asignacion de operadores logicos reutilizados - NOT*/
assign AIN_N = ~AIN;
assign BIN_N = ~BIN;
assign CIN_N = ~CIN;
assign DIN_N = ~DIN;


/*Expresiones logicas para cada segmento*/

//Segmento A: SA = Din'(Ain+Bin')+Ain'(Cin+BinDin)+BinCin+AinBin'Cin'
assign SA = (DIN_N) & (AIN | BIN_N) | 
            (AIN_N) & (CIN | (BIN & DIN)) | 
            (BIN & CIN) | 
            (AIN & BIN_N & CIN_N);  

//Segmento B: SB = Bin'(Ain' + Din') + Ain'(Cin ⊙ Din) + Ain Din Cin'
assign SB = (BIN_N) & (AIN_N | DIN_N) | 
            (AIN_N) & (~(CIN ^ DIN)) | 
            (AIN & DIN & CIN_N);

//Segmento C: SC = AinBin' + Ain'(Bin + Din + Cin') + DinCin'
assign SC = (AIN & BIN_N) | 
            (AIN_N) & (BIN | DIN | CIN_N) | 
            (DIN & CIN_N);   

//Segmento D: SD = Din'(Ain'Bin' + BinCin + AinCin') + Din(BinCin' + Bin'Cin)
assign SD = (DIN_N & (AIN_N & BIN_N | BIN & CIN | AIN & CIN_N)) | 
            (DIN & (BIN & CIN_N | BIN_N & CIN));

//Segmento E: SE = Din'(Bin'+Cin) + Ain(Cin + Bin)
assign SE = (DIN_N & (BIN_N | CIN)) | 
            (AIN & (CIN | BIN));

//Segmento F: SF = Ain(Cin + Bin') + Din'(Bin + Cin') + Ain'BinCin'
assign SF = (AIN & (CIN | BIN_N)) | 
            (DIN_N & (BIN | CIN_N)) | 
            (AIN_N & BIN & CIN_N);

//Segmento G: SG = Ain(Din + Bin') + Cin(Bin' + Din') + Ain'BinCin'
assign SG = (AIN & (DIN | BIN_N)) | 
            (CIN & (BIN_N | DIN_N)) | 
            (AIN_N & BIN & CIN_N);

/*Asignacion de los bits de salida */
assign segments[0] = SA;
assign segments[1] = SB;
assign segments[2] = SC;
assign segments[3] = SD;
assign segments[4] = SE;
assign segments[5] = SF;
assign segments[6] = SG;

endmodule



// ============================================================
// MODULO 5.3: Insercion de error
// Convencion usada:
// BitError = 3'b000 -> sin error
// BitError = 3'b001 -> invierte bit 0
// BitError = 3'b010 -> invierte bit 1
// ...
// BitError = 3'b111 -> invierte bit 6
// ============================================================
module error_inserter (
    input  logic [2:0] BitError,
    input  logic [6:0] WordHamming,
    output logic [6:0] transmision
);

    always @(*) begin
        transmision = WordHamming; // Copiar la palabra Hamming a la transmision inicialmente correcta

        if (BitError >= 1 && BitError <= 7)
            transmision[BitError-1] = ~WordHamming[BitError-1];

/*
        if (BitError < 7)
            // Inversión de un bit especifico en transmision según el valor de BitError
            transmision[BitError-1] = ~WordHamming[BitError-1];
        else
            // Si BitError es 7 o mayor, no se introduce ningún error (transmision ya es igual a WordHamming)
            transmision = WordHamming;
*/
    end

endmodule

src/Emisor/sim/top_tb.sv
`timescale 1ns/1ps

module top_tb;

    // Entradas
    logic [3:0] data_in;
    logic [2:0] BitError;

    // Salidas
    logic [6:0] code_out;
    logic [6:0] transmision;
    logic [6:0] seg;

    // DUT
    top dut (
        .data_in(data_in),
        .BitError(BitError),
        .code_out(code_out),
        .transmision(transmision),
        .seg(seg)
    );

    // Función Hamming esperada
    function automatic [6:0] expected_hamming (input [3:0] d);
        logic p1, p2, p4;
        begin
            p1 = d[3] ^ d[2] ^ d[0];
            p2 = d[3] ^ d[1] ^ d[0];
            p4 = d[2] ^ d[1] ^ d[0];

            expected_hamming[6] = p1;
            expected_hamming[5] = p2;
            expected_hamming[4] = d[3];
            expected_hamming[3] = p4;
            expected_hamming[2] = d[2];
            expected_hamming[1] = d[1];
            expected_hamming[0] = d[0];
        end
    endfunction

    logic [6:0] esperado_code;
    logic [6:0] esperado_tx;

    initial begin
        $display("=== INICIO DE TESTBENCH ===");

        for (int i = 0; i < 16; i++) begin
            data_in = i;

            for (int j = 0; j < 8; j++) begin
                BitError = j;
                #1;

                esperado_code = expected_hamming(data_in);
                esperado_tx   = esperado_code;

                // aplicar error esperado
                if (BitError >= 1 && BitError <= 7)
                    esperado_tx[BitError-1] = ~esperado_tx[BitError-1];

                // Verificación
                if (code_out !== esperado_code)
                    $display("ERROR CODE | data=%b esperado=%b got=%b",
                             data_in, esperado_code, code_out);

                if (transmision !== esperado_tx)
                    $display("ERROR TX | data=%b BitError=%b esperado=%b got=%b",
                             data_in, BitError, esperado_tx, transmision);
                else
                    $display("OK | data=%b BitError=%b",
                             data_in, BitError);
            end
        end

        $display("=== FIN DEL TESTBENCH ===");
        $finish;
    end

    initial begin
        $dumpfile("top_tb.vcd");
        $dumpvars(0, top_tb);
    end

endmodule

src/Emisor/build/top_tb.vcd
$date
	Thu Apr 09 13:54:22 2026
$end
$version
	Icarus Verilog
$end
$timescale
	1ps
$end
$scope module top_tb $end
$var wire 7 ! transmision [6:0] $end
$var wire 7 " seg [6:0] $end
$var wire 7 # code_out [6:0] $end
$var reg 3 $ BitError [2:0] $end
$var reg 4 % data_in [3:0] $end
$var reg 7 & esperado_code [6:0] $end
$var reg 7 ' esperado_tx [6:0] $end
$scope function expected_hamming $end
$upscope $end
$scope module dut $end
$var wire 3 ( BitError [2:0] $end
$var wire 4 ) data_in [3:0] $end
$var wire 7 * transmision [6:0] $end
$var wire 7 + seg [6:0] $end
$var wire 7 , code_out [6:0] $end
$scope module U1 $end
$var wire 4 - data_in [3:0] $end
$var reg 7 . code_out [6:0] $end
$var reg 1 / p1 $end
$var reg 1 0 p2 $end
$var reg 1 1 p4 $end
$upscope $end
$scope module U2 $end
$var wire 3 2 BitError [2:0] $end
$var wire 7 3 WordHamming [6:0] $end
$var reg 7 4 transmision [6:0] $end
$upscope $end
$scope module U3 $end
$var wire 1 5 AIN_N $end
$var wire 1 6 BIN_N $end
$var wire 1 7 CIN_N $end
$var wire 1 8 DIN_N $end
$var wire 1 9 SA $end
$var wire 1 : SB $end
$var wire 1 ; SC $end
$var wire 1 < SD $end
$var wire 1 = SE $end
$var wire 1 > SF $end
$var wire 1 ? SG $end
$var wire 4 @ sw [3:0] $end
$var wire 7 A segments [6:0] $end
$var wire 1 B DIN $end
$var wire 1 C CIN $end
$var wire 1 D BIN $end
$var wire 1 E AIN $end
$upscope $end
$upscope $end
$scope begin $ivl_for_loop0 $end
$var integer 32 F i [31:0] $end
$scope begin $ivl_for_loop1 $end
$var integer 32 G j [31:0] $end
$upscope $end
$upscope $end
$upscope $end
$enddefinitions $end
$comment Show the parameter values. $end
$dumpall
$end
#0
$dumpvars
b0 G
b0 F
0E
0D
0C
0B
b111111 A
b0 @
0?
1>
1=
1<
1;
1:
19
18
17
16
15
b0 4
b0 3
b0 2
01
00
0/
b0 .
b0 -
b0 ,
b111111 +
b0 *
b0 )
b0 (
bx '
bx &
b0 %
b0 $
b0 #
b111111 "
b0 !
$end
#1000
b1 !
b1 *
b1 4
b1 $
b1 (
b1 2
b1 G
b0 '
b0 &
#2000
b10 !
b10 *
b10 4
b10 $
b10 (
b10 2
b10 G
b1 '
#3000
b100 !
b100 *
b100 4
b11 $
b11 (
b11 2
b11 G
b10 '
#4000
b1000 !
b1000 *
b1000 4
b100 $
b100 (
b100 2
b100 G
b100 '
#5000
b10000 !
b10000 *
b10000 4
b101 $
b101 (
b101 2
b101 G
b1000 '
#6000
b100000 !
b100000 *
b100000 4
b110 $
b110 (
b110 2
b110 G
b10000 '
#7000
b1000000 !
b1000000 *
b1000000 4
b111 $
b111 (
b111 2
b111 G
b100000 '
#8000
09
0>
0<
b110 "
b110 +
b110 A
0=
08
b1101001 !
b1101001 *
b1101001 4
b1101001 #
b1101001 ,
b1101001 .
b1101001 3
11
10
1/
1B
b0 $
b0 (
b0 2
b1 %
b1 )
b1 -
b1 @
b1 F
b0 G
b1000000 '
#9000
b1101000 !
b1101000 *
b1101000 4
b1 $
b1 (
b1 2
b1 G
b1101001 '
b1101001 &
#10000
b1101011 !
b1101011 *
b1101011 4
b10 $
b10 (
b10 2
b10 G
b1101000 '
#11000
b1101101 !
b1101101 *
b1101101 4
b11 $
b11 (
b11 2
b11 G
b1101011 '
#12000
b1100001 !
b1100001 *
b1100001 4
b100 $
b100 (
b100 2
b100 G
b1101101 '
#13000
b1111001 !
b1111001 *
b1111001 4
b101 $
b101 (
b101 2
b101 G
b1100001 '
#14000
b1001001 !
b1001001 *
b1001001 4
b110 $
b110 (
b110 2
b110 G
b1111001 '
#15000
b101001 !
b101001 *
b101001 4
b111 $
b111 (
b111 2
b111 G
b1001001 '
#16000
0;
19
0>
1?
1<
b1011011 "
b1011011 +
b1011011 A
1=
07
18
b101010 !
b101010 *
b101010 4
b101010 #
b101010 ,
b101010 .
b101010 3
0/
1C
0B
b0 $
b0 (
b0 2
b10 %
b10 )
b10 -
b10 @
b10 F
b0 G
b101001 '
#17000
b101011 !
b101011 *
b101011 4
b1 $
b1 (
b1 2
b1 G
b101010 '
b101010 &
#18000
b101000 !
b101000 *
b101000 4
b10 $
b10 (
b10 2
b10 G
b101011 '
#19000
b101110 !
b101110 *
b101110 4
b11 $
b11 (
b11 2
b11 G
b101000 '
#20000
b100010 !
b100010 *
b100010 4
b100 $
b100 (
b100 2
b100 G
b101110 '
#21000
b111010 !
b111010 *
b111010 4
b101 $
b101 (
b101 2
b101 G
b100010 '
#22000
b1010 !
b1010 *
b1010 4
b110 $
b110 (
b110 2
b110 G
b111010 '
#23000
b1101010 !
b1101010 *
b1101010 4
b111 $
b111 (
b111 2
b111 G
b1010 '
#24000
1;
b1001111 "
b1001111 +
b1001111 A
0=
08
b1000011 !
b1000011 *
b1000011 4
b1000011 #
b1000011 ,
b1000011 .
b1000011 3
01
00
1/
1B
b0 $
b0 (
b0 2
b11 %
b11 )
b11 -
b11 @
b11 F
b0 G
b1101010 '
#25000
b1000010 !
b1000010 *
b1000010 4
b1 $
b1 (
b1 2
b1 G
b1000011 '
b1000011 &
#26000
b1000001 !
b1000001 *
b1000001 4
b10 $
b10 (
b10 2
b10 G
b1000010 '
#27000
b1000111 !
b1000111 *
b1000111 4
b11 $
b11 (
b11 2
b11 G
b1000001 '
#28000
b1001011 !
b1001011 *
b1001011 4
b100 $
b100 (
b100 2
b100 G
b1000111 '
#29000
b1010011 !
b1010011 *
b1010011 4
b101 $
b101 (
b101 2
b101 G
b1001011 '
#30000
b1100011 !
b1100011 *
b1100011 4
b110 $
b110 (
b110 2
b110 G
b1010011 '
#31000
b11 !
b11 *
b11 4
b111 $
b111 (
b111 2
b111 G
b1100011 '
#32000
09
0<
1>
b1100110 "
b1100110 +
b1100110 A
0=
06
17
18
b1001100 !
b1001100 *
b1001100 4
b1001100 #
b1001100 ,
b1001100 .
b1001100 3
11
1D
0C
0B
b0 $
b0 (
b0 2
b100 %
b100 )
b100 -
b100 @
b100 F
b0 G
b11 '
#33000
b1001101 !
b1001101 *
b1001101 4
b1 $
b1 (
b1 2
b1 G
b1001100 '
b1001100 &
#34000
b1001110 !
b1001110 *
b1001110 4
b10 $
b10 (
b10 2
b10 G
b1001101 '
#35000
b1001000 !
b1001000 *
b1001000 4
b11 $
b11 (
b11 2
b11 G
b1001110 '
#36000
b1000100 !
b1000100 *
b1000100 4
b100 $
b100 (
b100 2
b100 G
b1001000 '
#37000
b1011100 !
b1011100 *
b1011100 4
b101 $
b101 (
b101 2
b101 G
b1000100 '
#38000
b1101100 !
b1101100 *
b1101100 4
b110 $
b110 (
b110 2
b110 G
b1011100 '
#39000
b1100 !
b1100 *
b1100 4
b111 $
b111 (
b111 2
b111 G
b1101100 '
#40000
19
0:
b1101101 "
b1101101 +
b1101101 A
1<
08
b100101 !
b100101 *
b100101 4
b100101 #
b100101 ,
b100101 .
b100101 3
01
10
0/
1B
b0 $
b0 (
b0 2
b101 %
b101 )
b101 -
b101 @
b101 F
b0 G
b1100 '
#41000
b100100 !
b100100 *
b100100 4
b1 $
b1 (
b1 2
b1 G
b100101 '
b100101 &
#42000
b100111 !
b100111 *
b100111 4
b10 $
b10 (
b10 2
b10 G
b100100 '
#43000
b100001 !
b100001 *
b100001 4
b11 $
b11 (
b11 2
b11 G
b100111 '
#44000
b101101 !
b101101 *
b101101 4
b100 $
b100 (
b100 2
b100 G
b100001 '
#45000
b110101 !
b110101 *
b110101 4
b101 $
b101 (
b101 2
b101 G
b101101 '
#46000
b101 !
b101 *
b101 4
b110 $
b110 (
b110 2
b110 G
b110101 '
#47000
b1100101 !
b1100101 *
b1100101 4
b111 $
b111 (
b111 2
b111 G
b101 '
#48000
1?
1=
b1111101 "
b1111101 +
b1111101 A
1<
07
18
b1100110 !
b1100110 *
b1100110 4
b1100110 #
b1100110 ,
b1100110 .
b1100110 3
1/
1C
0B
b0 $
b0 (
b0 2
b110 %
b110 )
b110 -
b110 @
b110 F
b0 G
b1100101 '
#49000
b1100111 !
b1100111 *
b1100111 4
b1 $
b1 (
b1 2
b1 G
b1100110 '
b1100110 &
#50000
b1100100 !
b1100100 *
b1100100 4
b10 $
b10 (
b10 2
b10 G
b1100111 '
#51000
b1100010 !
b1100010 *
b1100010 4
b11 $
b11 (
b11 2
b11 G
b1100100 '
#52000
b1101110 !
b1101110 *
b1101110 4
b100 $
b100 (
b100 2
b100 G
b1100010 '
#53000
b1110110 !
b1110110 *
b1110110 4
b101 $
b101 (
b101 2
b101 G
b1101110 '
#54000
b1000110 !
b1000110 *
b1000110 4
b110 $
b110 (
b110 2
b110 G
b1110110 '
#55000
b100110 !
b100110 *
b100110 4
b111 $
b111 (
b111 2
b111 G
b1000110 '
#56000
1:
0?
0>
0<
b111 "
b111 +
b111 A
0=
08
b1111 !
b1111 *
b1111 4
b1111 #
b1111 ,
b1111 .
b1111 3
11
00
0/
1B
b0 $
b0 (
b0 2
b111 %
b111 )
b111 -
b111 @
b111 F
b0 G
b100110 '
#57000
b1110 !
b1110 *
b1110 4
b1 $
b1 (
b1 2
b1 G
b1111 '
b1111 &
#58000
b1101 !
b1101 *
b1101 4
b10 $
b10 (
b10 2
b10 G
b1110 '
#59000
b1011 !
b1011 *
b1011 4
b11 $
b11 (
b11 2
b11 G
b1101 '
#60000
b111 !
b111 *
b111 4
b100 $
b100 (
b100 2
b100 G
b1011 '
#61000
b11111 !
b11111 *
b11111 4
b101 $
b101 (
b101 2
b101 G
b111 '
#62000
b101111 !
b101111 *
b101111 4
b110 $
b110 (
b110 2
b110 G
b11111 '
#63000
b1001111 !
b1001111 *
b1001111 4
b111 $
b111 (
b111 2
b111 G
b101111 '
#64000
1?
1=
1>
b1111111 "
b1111111 +
b1111111 A
1<
05
16
17
18
b1110000 !
b1110000 *
b1110000 4
b1110000 #
b1110000 ,
b1110000 .
b1110000 3
01
10
1/
1E
0D
0C
0B
b0 $
b0 (
b0 2
b1000 %
b1000 )
b1000 -
b1000 @
b1000 F
b0 G
b1001111 '
#65000
b1110001 !
b1110001 *
b1110001 4
b1 $
b1 (
b1 2
b1 G
b1110000 '
b1110000 &
#66000
b1110010 !
b1110010 *
b1110010 4
b10 $
b10 (
b10 2
b10 G
b1110001 '
#67000
b1110100 !
b1110100 *
b1110100 4
b11 $
b11 (
b11 2
b11 G
b1110010 '
#68000
b1111000 !
b1111000 *
b1111000 4
b100 $
b100 (
b100 2
b100 G
b1110100 '
#69000
b1100000 !
b1100000 *
b1100000 4
b101 $
b101 (
b101 2
b101 G
b1111000 '
#70000
b1010000 !
b1010000 *
b1010000 4
b110 $
b110 (
b110 2
b110 G
b1100000 '
#71000
b110000 !
b110000 *
b110000 4
b111 $
b111 (
b111 2
b111 G
b1010000 '
#72000
0<
b1100111 "
b1100111 +
b1100111 A
0=
08
b11001 !
b11001 *
b11001 4
b11001 #
b11001 ,
b11001 .
b11001 3
11
00
0/
1B
b0 $
b0 (
b0 2
b1001 %
b1001 )
b1001 -
b1001 @
b1001 F
b0 G
b110000 '
#73000
b11000 !
b11000 *
b11000 4
b1 $
b1 (
b1 2
b1 G
b11001 '
b11001 &
#74000
b11011 !
b11011 *
b11011 4
b10 $
b10 (
b10 2
b10 G
b11000 '
#75000
b11101 !
b11101 *
b11101 4
b11 $
b11 (
b11 2
b11 G
b11011 '
#76000
b10001 !
b10001 *
b10001 4
b100 $
b100 (
b100 2
b100 G
b11101 '
#77000
b1001 !
b1001 *
b1001 4
b101 $
b101 (
b101 2
b101 G
b10001 '
#78000
b111001 !
b111001 *
b111001 4
b110 $
b110 (
b110 2
b110 G
b1001 '
#79000
b1011001 !
b1011001 *
b1011001 4
b111 $
b111 (
b111 2
b111 G
b111001 '
#80000
19
1:
0<
b1110111 "
b1110111 +
b1110111 A
1=
07
18
b1011010 !
b1011010 *
b1011010 4
b1011010 #
b1011010 ,
b1011010 .
b1011010 3
1/
1C
0B
b0 $
b0 (
b0 2
b1010 %
b1010 )
b1010 -
b1010 @
b1010 F
b0 G
b1011001 '
#81000
b1011011 !
b1011011 *
b1011011 4
b1 $
b1 (
b1 2
b1 G
b1011010 '
b1011010 &
#82000
b1011000 !
b1011000 *
b1011000 4
b10 $
b10 (
b10 2
b10 G
b1011011 '
#83000
b1011110 !
b1011110 *
b1011110 4
b11 $
b11 (
b11 2
b11 G
b1011000 '
#84000
b1010010 !
b1010010 *
b1010010 4
b100 $
b100 (
b100 2
b100 G
b1011110 '
#85000
b1001010 !
b1001010 *
b1001010 4
b101 $
b101 (
b101 2
b101 G
b1010010 '
#86000
b1111010 !
b1111010 *
b1111010 4
b110 $
b110 (
b110 2
b110 G
b1001010 '
#87000
b11010 !
b11010 *
b11010 4
b111 $
b111 (
b111 2
b111 G
b1111010 '
#88000
09
0:
b1111100 "
b1111100 +
b1111100 A
1<
08
b110011 !
b110011 *
b110011 4
b110011 #
b110011 ,
b110011 .
b110011 3
01
10
0/
1B
b0 $
b0 (
b0 2
b1011 %
b1011 )
b1011 -
b1011 @
b1011 F
b0 G
b11010 '
#89000
b110010 !
b110010 *
b110010 4
b1 $
b1 (
b1 2
b1 G
b110011 '
b110011 &
#90000
b110001 !
b110001 *
b110001 4
b10 $
b10 (
b10 2
b10 G
b110010 '
#91000
b110111 !
b110111 *
b110111 4
b11 $
b11 (
b11 2
b11 G
b110001 '
#92000
b111011 !
b111011 *
b111011 4
b100 $
b100 (
b100 2
b100 G
b110111 '
#93000
b100011 !
b100011 *
b100011 4
b101 $
b101 (
b101 2
b101 G
b111011 '
#94000
b10011 !
b10011 *
b10011 4
b110 $
b110 (
b110 2
b110 G
b100011 '
#95000
b1110011 !
b1110011 *
b1110011 4
b111 $
b111 (
b111 2
b111 G
b10011 '
#96000
0?
0;
19
b111001 "
b111001 +
b111001 A
1<
06
17
18
b111100 !
b111100 *
b111100 4
b111100 #
b111100 ,
b111100 .
b111100 3
11
1D
0C
0B
b0 $
b0 (
b0 2
b1100 %
b1100 )
b1100 -
b1100 @
b1100 F
b0 G
b1110011 '
#97000
b111101 !
b111101 *
b111101 4
b1 $
b1 (
b1 2
b1 G
b111100 '
b111100 &
#98000
b111110 !
b111110 *
b111110 4
b10 $
b10 (
b10 2
b10 G
b111101 '
#99000
b111000 !
b111000 *
b111000 4
b11 $
b11 (
b11 2
b11 G
b111110 '
#100000
b110100 !
b110100 *
b110100 4
b100 $
b100 (
b100 2
b100 G
b111000 '
#101000
b101100 !
b101100 *
b101100 4
b101 $
b101 (
b101 2
b101 G
b110100 '
#102000
b11100 !
b11100 *
b11100 4
b110 $
b110 (
b110 2
b110 G
b101100 '
#103000
b1111100 !
b1111100 *
b1111100 4
b111 $
b111 (
b111 2
b111 G
b11100 '
#104000
09
1?
0>
1:
b1011110 "
b1011110 +
b1011110 A
1;
08
b1010101 !
b1010101 *
b1010101 4
b1010101 #
b1010101 ,
b1010101 .
b1010101 3
01
00
1/
1B
b0 $
b0 (
b0 2
b1101 %
b1101 )
b1101 -
b1101 @
b1101 F
b0 G
b1111100 '
#105000
b1010100 !
b1010100 *
b1010100 4
b1 $
b1 (
b1 2
b1 G
b1010101 '
b1010101 &
#106000
b1010111 !
b1010111 *
b1010111 4
b10 $
b10 (
b10 2
b10 G
b1010100 '
#107000
b1010001 !
b1010001 *
b1010001 4
b11 $
b11 (
b11 2
b11 G
b1010111 '
#108000
b1011101 !
b1011101 *
b1011101 4
b100 $
b100 (
b100 2
b100 G
b1010001 '
#109000
b1000101 !
b1000101 *
b1000101 4
b101 $
b101 (
b101 2
b101 G
b1011101 '
#110000
b1110101 !
b1110101 *
b1110101 4
b110 $
b110 (
b110 2
b110 G
b1000101 '
#111000
b10101 !
b10101 *
b10101 4
b111 $
b111 (
b111 2
b111 G
b1110101 '
#112000
1>
19
0:
b1111001 "
b1111001 +
b1111001 A
0;
07
18
b10110 !
b10110 *
b10110 4
b10110 #
b10110 ,
b10110 .
b10110 3
0/
1C
0B
b0 $
b0 (
b0 2
b1110 %
b1110 )
b1110 -
b1110 @
b1110 F
b0 G
b10101 '
#113000
b10111 !
b10111 *
b10111 4
b1 $
b1 (
b1 2
b1 G
b10110 '
b10110 &
#114000
b10100 !
b10100 *
b10100 4
b10 $
b10 (
b10 2
b10 G
b10111 '
#115000
b10010 !
b10010 *
b10010 4
b11 $
b11 (
b11 2
b11 G
b10100 '
#116000
b11110 !
b11110 *
b11110 4
b100 $
b100 (
b100 2
b100 G
b10010 '
#117000
b110 !
b110 *
b110 4
b101 $
b101 (
b101 2
b101 G
b11110 '
#118000
b110110 !
b110110 *
b110110 4
b110 $
b110 (
b110 2
b110 G
b110 '
#119000
b1010110 !
b1010110 *
b1010110 4
b111 $
b111 (
b111 2
b111 G
b110110 '
#120000
b1110001 "
b1110001 +
b1110001 A
0<
08
b1111111 !
b1111111 *
b1111111 4
b1111111 #
b1111111 ,
b1111111 .
b1111111 3
11
10
1/
1B
b0 $
b0 (
b0 2
b1111 %
b1111 )
b1111 -
b1111 @
b1111 F
b0 G
b1010110 '
#121000
b1111110 !
b1111110 *
b1111110 4
b1 $
b1 (
b1 2
b1 G
b1111111 '
b1111111 &
#122000
b1111101 !
b1111101 *
b1111101 4
b10 $
b10 (
b10 2
b10 G
b1111110 '
#123000
b1111011 !
b1111011 *
b1111011 4
b11 $
b11 (
b11 2
b11 G
b1111101 '
#124000
b1110111 !
b1110111 *
b1110111 4
b100 $
b100 (
b100 2
b100 G
b1111011 '
#125000
b1101111 !
b1101111 *
b1101111 4
b101 $
b101 (
b101 2
b101 G
b1110111 '
#126000
b1011111 !
b1011111 *
b1011111 4
b110 $
b110 (
b110 2
b110 G
b1101111 '
#127000
b111111 !
b111111 *
b111111 4
b111 $
b111 (
b111 2
b111 G
b1011111 '
#128000
b10000 F
b1000 G
b111111 '
